durian/__init__.py
durian/console.py
durian/ctools.py
durian/gui.py
durian/network.py
durian/os.py
durian/tools.py
durian/user.py
SDurian-1.0.1.dist-info/LICENSE.txt
SDurian-1.0.1.dist-info/METADATA
SDurian-1.0.1.dist-info/WHEEL
SDurian-1.0.1.dist-info/top_level.txt
SDurian-1.0.1.dist-info/RECORD
